.gitignore
AUTHORS.rst
CONTRIBUTING.rst
HISTORY.rst
LICENSE
MANIFEST.in
README.rst
requirements_dev.txt
setup.cfg
setup.py
test_settings.py
tox.ini
django_payments_mercadopago.egg-info/PKG-INFO
django_payments_mercadopago.egg-info/SOURCES.txt
django_payments_mercadopago.egg-info/dependency_links.txt
django_payments_mercadopago.egg-info/not-zip-safe
django_payments_mercadopago.egg-info/requires.txt
django_payments_mercadopago.egg-info/top_level.txt
docs/Makefile
docs/authors.rst
docs/conf.py
docs/contributing.rst
docs/history.rst
docs/index.rst
docs/installation.rst
docs/make.bat
docs/readme.rst
docs/usage.rst
payments_mercadopago/__init__.py
payments_mercadopago/test_mercadopago.py