Metadata-Version: 1.2
Name: django-payments-mercadopago
Version: 0.4.1
Summary: A mercadopago payment gateway backend for django-payments.
Home-page: https://github.com/EduardoZepeda/django-payments-mercadopago
Author: Eduardo Zepeda
Author-email: eduardozepeda@coffeebytes.dev
License: MIT license
Download-URL: https://github.com/EduardoZepeda/django-payments-mercadopago/archive/0.4.0.tar.gz
Keywords: django-payments,mercadopago,django
Platform: UNKNOWN
Classifier: Development Status :: 3 - Alpha
Classifier: Intended Audience :: Developers
Classifier: License :: OSI Approved :: MIT License
Classifier: Natural Language :: English
Classifier: Programming Language :: Python :: 3
Classifier: Programming Language :: Python :: 3.6
Classifier: Programming Language :: Python :: 3.7
Classifier: Programming Language :: Python :: 3.8
Requires-Python: >=3.5
